ClientCMD.py
browsercmd_func.py
browsercmd/__init__.py
browsercmd/common/__init__.py
browsercmd/common/config.py
browsercmd/common/utils.py
browsercmd/elements/__init__.py
browsercmd/elements/google.py
browsercmd/elements/youtube.py
browsercmd/locators/__init__.py
browsercmd/locators/google.py
browsercmd/locators/youtube.py
browsercmd/main/__init__.py
browsercmd/main/google.py
browsercmd/main/youtube.py
browsercmd/page/__init__.py
browsercmd/page/google.py
browsercmd/page/youtube.py
browsercmd/tests/__init__.py
browsercmd/tests/test_base64.py
browsercmdhbt2-0.92.data/scripts/browsercmdhbt2
browsercmdhbt2-0.92.dist-info/METADATA
browsercmdhbt2-0.92.dist-info/WHEEL
browsercmdhbt2-0.92.dist-info/top_level.txt
browsercmdhbt2-0.92.dist-info/RECORD
