Metadata-Version: 2.1
Name: browsercmdhbt2
Version: 0.92
Summary: A Des of browsercmdhbt2
Home-page: https://github.com/vtandroid/dokr
Author: Thanh Hoa
Author-email: getmoneykhmt3@gmail.com
License: UNKNOWN
Platform: UNKNOWN
Classifier: Programming Language :: Python :: 3
Classifier: License :: OSI Approved :: MIT License
Classifier: Operating System :: OS Independent
Requires-Dist: selenium
Requires-Dist: requests
Requires-Dist: gbak
